LICENSE
README.md
setup.py
notdb/Files.py
notdb/UTypes.py
notdb/__init__.py
notdb/__main__.py
notdb/algo.py
notdb/encrypt.py
notdb/errors.py
notdb/filesHandler.py
notdb/ndb.py
notdb/popHandler.py
notdb.egg-info/PKG-INFO
notdb.egg-info/SOURCES.txt
notdb.egg-info/dependency_links.txt
notdb.egg-info/entry_points.txt
notdb.egg-info/not-zip-safe
notdb.egg-info/requires.txt
notdb.egg-info/top_level.txt