Metadata-Version: 2.1
Name: notdb
Version: 1.2.3
Summary: NotDB PYON-like database
Home-page: https://github.com/nawafalqari/NotDB/
Author: Nawaf Alqari
Author-email: nawafalqari13@gmail.com
License: MIT
Project-URL: Documentation, https://github.com/nawafalqari/NotDB#readme
Project-URL: Bug Tracker, https://github.com/nawafalqari/NotDB/issues
Project-URL: Source Code, https://github.com/nawafalqari/NotDB/
Project-URL: Discord, https://discord.gg/cpvynqk4XT
Project-URL: Donate, https://paypal.me/NawafHAlqari
Keywords: notdb,db,database,notdatabsae,simple database
Platform: UNKNOWN
Classifier: Programming Language :: Python :: 3
Classifier: License :: OSI Approved :: MIT License
Classifier: Operating System :: OS Independent
Classifier: Topic :: Database
License-File: LICENSE
